{
  "pageNumber": 127,
  "riwayaId": "warsh",
  "ayahs": [
    {
      "text": "إ︎ِ︎ذ︎ْ︎ ق︎َ︎ا︎ل︎َ︎ ا︎َ︎۬︎ل︎ْ︎ح︎َ︎و︎َ︎ا︎ر︎ِ︎ي︎ّ︎ُ︎و︎ن︎َ︎ ي︎َ︎ٰ︎ع︎ِ︎ي︎س︎َ︎ي︎ ا︎َ︎۪︎ب︎ْ︎ن︎َ︎ م︎َ︎ر︎ْ︎ي︎َ︎م︎َ︎ ه︎َ︎ل︎ْ︎ ي︎َ︎س︎ْ︎ت︎َ︎ط︎ِ︎ي︎ع︎ُ︎ ر︎َ︎ب︎ّ︎ُ︎ك︎َ︎ أ︎َ︎ن︎ْ︎ ي︎ّ︎ُ︎ن︎َ︎ز︎ّ︎ِ︎ل︎َ︎ ع︎َ︎ل︎َ︎ي︎ْ︎ن︎َ︎ا︎ م︎َ︎ا︎ٓ︎ئ︎ِ︎د︎َ︎ة︎ٗ︎ م︎ّ︎ِ︎ن︎َ︎ ا︎َ︎۬︎ل︎س︎ّ︎َ︎م︎َ︎ا︎ٓ︎ء︎ِ︎ۖ︎ ق︎َ︎ا︎ل︎َ︎ ا︎َ︎۪︎ت︎ّ︎َ︎ق︎ُ︎و︎ا︎ْ︎ ا︎ُ︎۬︎ل︎ل︎ّ︎َ︎ه︎َ︎ إ︎ِ︎ن︎ ك︎ُ︎ن︎ت︎ُ︎م︎ م︎ّ︎ُ︎و︎م︎ِ︎ن︎ِ︎ي︎ن︎َ︎ۖ︎ ١︎١︎٤︎",
      "numberInSurah": 114,
      "verse_key": "5:114"
    },
    {
      "text": "ق︎َ︎ا︎ل︎ُ︎و︎ا︎ْ︎ ن︎ُ︎ر︎ِ︎ي︎د︎ُ︎ أ︎َ︎ن︎ ن︎ّ︎َ︎ا︎ك︎ُ︎ل︎َ︎ م︎ِ︎ن︎ْ︎ه︎َ︎ا︎ و︎َ︎ت︎َ︎ط︎ْ︎م︎َ︎ئ︎ِ︎ن︎ّ︎َ︎ ق︎ُ︎ل︎ُ︎و︎ب︎ُ︎ن︎َ︎ا︎ و︎َ︎ن︎َ︎ع︎ْ︎ل︎َ︎م︎َ︎ أ︎َ︎ن︎ ق︎َ︎د︎ْ︎ ص︎َ︎د︎َ︎ق︎ْ︎ت︎َ︎ن︎َ︎ا︎ و︎َ︎ن︎َ︎ك︎ُ︎و︎ن︎َ︎ ع︎َ︎ل︎َ︎ي︎ْ︎ه︎َ︎ا︎ م︎ِ︎ن︎َ︎ ا︎َ︎۬︎ل︎ش︎ّ︎َ︎ٰ︎ه︎ِ︎د︎ِ︎ي︎ن︎َ︎ۖ︎ ١︎١︎٥︎",
      "numberInSurah": 115,
      "verse_key": "5:115"
    },
    {
      "text": "ق︎َ︎ا︎ل︎َ︎ ع︎ِ︎ي︎س︎َ︎ي︎ ا︎َ︎۪︎ب︎ْ︎ن︎ُ︎ م︎َ︎ر︎ْ︎ي︎َ︎م︎َ︎ ا︎َ︎۬︎ل︎ل︎ّ︎َ︎ه︎ُ︎م︎ّ︎َ︎ ر︎َ︎ب︎ّ︎َ︎ن︎َ︎ا︎ٓ︎ أ︎َ︎ن︎ز︎ِ︎ل︎ْ︎ ع︎َ︎ل︎َ︎ي︎ْ︎ن︎َ︎ا︎ م︎َ︎ا︎ٓ︎ئ︎ِ︎د︎َ︎ة︎ٗ︎ م︎ّ︎ِ︎ن︎َ︎ ا︎َ︎۬︎ل︎س︎ّ︎َ︎م︎َ︎ا︎ٓ︎ء︎ِ︎ ت︎َ︎ك︎ُ︎و︎ن︎ُ︎ ل︎َ︎ن︎َ︎ا︎ ع︎ِ︎ي︎د︎ا︎ٗ︎ ل︎ّ︎ِ︎أ︎َ︎و︎ّ︎َ︎ل︎ِ︎ن︎َ︎ا︎ و︎َ︎ء︎َ︎ا︎خ︎ِ︎ر︎ِ︎ن︎َ︎ا︎ و︎َ︎ء︎َ︎ا︎ي︎َ︎ة︎ٗ︎ م︎ّ︎ِ︎ن︎ك︎َ︎ۖ︎ و︎َ︎ا︎ر︎ْ︎ز︎ُ︎ق︎ْ︎ن︎َ︎ا︎ و︎َ︎أ︎َ︎ن︎ت︎َ︎ خ︎َ︎ي︎ْ︎ر︎ُ︎ ا︎ُ︎۬︎ل︎ر︎ّ︎َ︎ٰ︎ز︎ِ︎ق︎ِ︎ي︎ن︎َ︎ۖ︎ ١︎١︎٦︎",
      "numberInSurah": 116,
      "verse_key": "5:116"
    },
    {
      "text": "ق︎َ︎ا︎ل︎َ︎ ا︎َ︎۬︎ل︎ل︎ّ︎َ︎ه︎ُ︎ إ︎ِ︎ن︎ّ︎ِ︎ے︎ م︎ُ︎ن︎َ︎ز︎ّ︎ِ︎ل︎ُ︎ه︎َ︎ا︎ ع︎َ︎ل︎َ︎ي︎ْ︎ك︎ُ︎م︎ْ︎ ف︎َ︎م︎َ︎ن︎ْ︎ ي︎ّ︎َ︎ك︎ْ︎ف︎ُ︎ر︎ْ︎ ب︎َ︎ع︎ْ︎د︎ُ︎ م︎ِ︎ن︎ك︎ُ︎م︎ْ︎ ف︎َ︎إ︎ِ︎ن︎ّ︎ِ︎ي︎َ︎ أ︎ُ︎ع︎َ︎ذ︎ّ︎ِ︎ب︎ُ︎ه︎ُ︎ۥ︎ ع︎َ︎ذ︎َ︎ا︎ب︎ا︎ٗ︎ ل︎ّ︎َ︎ا︎ٓ︎ أ︎ُ︎ع︎َ︎ذ︎ّ︎ِ︎ب︎ُ︎ه︎ُ︎ۥ︎ٓ︎ أ︎َ︎ح︎َ︎د︎ا︎ٗ︎ م︎ّ︎ِ︎ن︎َ︎ ا︎َ︎۬︎ل︎ْ︎ع︎َ︎ٰ︎ل︎َ︎م︎ِ︎ي︎ن︎َ︎ۖ︎ ١︎١︎٧︎",
      "numberInSurah": 117,
      "verse_key": "5:117"
    },
    {
      "text": "و︎َ︎إ︎ِ︎ذ︎ْ︎ ق︎َ︎ا︎ل︎َ︎ ا︎َ︎۬︎ل︎ل︎ّ︎َ︎ه︎ُ︎ ي︎َ︎ٰ︎ع︎ِ︎ي︎س︎َ︎ي︎ ا︎َ︎۪︎ب︎ْ︎ن︎َ︎ م︎َ︎ر︎ْ︎ي︎َ︎م︎َ︎ ء︎َ︎ا︎ٓ︎ن︎ت︎َ︎ ق︎ُ︎ل︎ْ︎ت︎َ︎ ل︎ِ︎ل︎ن︎ّ︎َ︎ا︎س︎ِ︎ ا︎ِ︎۪︎ت︎ّ︎َ︎خ︎ِ︎ذ︎ُ︎و︎ن︎ِ︎ے︎ و︎َ︎أ︎ُ︎م︎ّ︎ِ︎ي︎َ︎ إ︎ِ︎ل︎َ︎ٰ︎ه︎َ︎ي︎ْ︎ن︎ِ︎ م︎ِ︎ن︎ د︎ُ︎و︎ن︎ِ︎ ا︎ِ︎۬︎ل︎ل︎ّ︎َ︎ه︎ِ︎ۖ︎ ق︎َ︎ا︎ل︎َ︎ س︎ُ︎ب︎ْ︎ح︎َ︎ٰ︎ن︎َ︎ك︎َ︎ م︎َ︎ا︎ ي︎َ︎ك︎ُ︎و︎ن︎ُ︎ ل︎ِ︎ي︎َ︎ أ︎َ︎ن︎َ︎ ا︎َ︎ق︎ُ︎و︎ل︎َ︎ م︎َ︎ا︎ ل︎َ︎ي︎ْ︎س︎َ︎ ل︎ِ︎ے︎ ب︎ِ︎ح︎َ︎ق︎ّ︎ٍ︎ۖ︎ ا︎ِ︎ن︎ ك︎ُ︎ن︎ت︎ُ︎ ق︎ُ︎ل︎ْ︎ت︎ُ︎ه︎ُ︎ۥ︎ ف︎َ︎ق︎َ︎د︎ْ︎ ع︎َ︎ل︎ِ︎م︎ْ︎ت︎َ︎ه︎ُ︎ۥ︎ۖ︎ ت︎َ︎ع︎ْ︎ل︎َ︎م︎ُ︎ م︎َ︎ا︎ ف︎ِ︎ے︎ ن︎َ︎ف︎ْ︎س︎ِ︎ے︎ و︎َ︎ل︎َ︎ا︎ٓ︎ أ︎َ︎ع︎ْ︎ل︎َ︎م︎ُ︎ م︎َ︎ا︎ ف︎ِ︎ے︎ ن︎َ︎ف︎ْ︎س︎ِ︎ك︎َ︎ۖ︎ إ︎ِ︎ن︎ّ︎َ︎ك︎َ︎ أ︎َ︎ن︎ت︎َ︎ ع︎َ︎ل︎ّ︎َ︎ٰ︎م︎ُ︎ ا︎ُ︎۬︎ل︎ْ︎غ︎ُ︎ي︎ُ︎و︎ب︎ِ︎ۖ︎ ١︎١︎٨︎",
      "numberInSurah": 118,
      "verse_key": "5:118"
    },
    {
      "text": "م︎َ︎ا︎ ق︎ُ︎ل︎ْ︎ت︎ُ︎ ل︎َ︎ه︎ُ︎م︎ُ︎ۥ︎ٓ︎ إ︎ِ︎ل︎ّ︎َ︎ا︎ م︎َ︎ا︎ٓ︎ أ︎َ︎م︎َ︎ر︎ْ︎ت︎َ︎ن︎ِ︎ے︎ ب︎ِ︎ه︎ِ︎ۦ︎ٓ︎ أ︎َ︎ن︎ُ︎ ا︎ُ︎۟︎ع︎ْ︎ب︎ُ︎د︎ُ︎و︎ا︎ْ︎ ا︎ُ︎۬︎ل︎ل︎ّ︎َ︎ه︎َ︎ ر︎َ︎ب︎ّ︎ِ︎ے︎ و︎َ︎ر︎َ︎ب︎ّ︎َ︎ك︎ُ︎م︎ْ︎ۖ︎ و︎َ︎ك︎ُ︎ن︎ت︎ُ︎ ع︎َ︎ل︎َ︎ي︎ْ︎ه︎ِ︎م︎ْ︎ ش︎َ︎ه︎ِ︎ي︎د︎ا︎ٗ︎ م︎ّ︎َ︎ا︎ د︎ُ︎م︎ْ︎ت︎ُ︎ ف︎ِ︎ي︎ه︎ِ︎م︎ْ︎ۖ︎ ف︎َ︎ل︎َ︎م︎ّ︎َ︎ا︎ ت︎َ︎و︎َ︎ف︎ّ︎َ︎ي︎ْ︎ت︎َ︎ن︎ِ︎ے︎ ك︎ُ︎ن︎ت︎َ︎ أ︎َ︎ن︎ت︎َ︎ ا︎َ︎۬︎ل︎ر︎ّ︎َ︎ق︎ِ︎ي︎ب︎َ︎ ع︎َ︎ل︎َ︎ي︎ْ︎ه︎ِ︎م︎ْ︎ۖ︎ و︎َ︎أ︎َ︎ن︎ت︎َ︎ ع︎َ︎ل︎َ︎ي︎ٰ︎ ك︎ُ︎ل︎ّ︎ِ︎ ش︎َ︎ے︎ْ︎ء︎ٖ︎ ش︎َ︎ه︎ِ︎ي︎د︎ٌ︎ۖ︎ ١︎١︎٩︎",
      "numberInSurah": 119,
      "verse_key": "5:119"
    },
    {
      "text": "ا︎ِ︎ن︎ ت︎ُ︎ع︎َ︎ذ︎ّ︎ِ︎ب︎ْ︎ه︎ُ︎م︎ْ︎ ف︎َ︎إ︎ِ︎ن︎ّ︎َ︎ه︎ُ︎م︎ْ︎ ع︎ِ︎ب︎َ︎ا︎د︎ُ︎ك︎َ︎ۖ︎ و︎َ︎إ︎ِ︎ن︎ ت︎َ︎غ︎ْ︎ف︎ِ︎ر︎ْ︎ ل︎َ︎ه︎ُ︎م︎ْ︎ ف︎َ︎إ︎ِ︎ن︎ّ︎َ︎ك︎َ︎ أ︎َ︎ن︎ت︎َ︎ ا︎َ︎۬︎ل︎ْ︎ع︎َ︎ز︎ِ︎ي︎ز︎ُ︎ ا︎ُ︎۬︎ل︎ْ︎ح︎َ︎ك︎ِ︎ي︎م︎ُ︎ۖ︎ ١︎٢︎٠︎",
      "numberInSurah": 120,
      "verse_key": "5:120"
    }
  ],
  "source": {
    "type": "warsh-quran-apk",
    "timestamp": "2026-04-27T01:24:43.087Z"
  }
}