{
  "pageNumber": 521,
  "riwayaId": "warsh",
  "ayahs": [
    {
      "text": "و︎َ︎ا︎ل︎س︎ّ︎َ︎م︎َ︎ا︎ٓ︎ء︎ِ︎ ذ︎َ︎ا︎ت︎ِ︎ ا︎ِ︎۬︎ل︎ْ︎ح︎ُ︎ب︎ُ︎ك︎ِ︎ ٧︎",
      "numberInSurah": 7,
      "verse_key": "51:7"
    },
    {
      "text": "إ︎ِ︎ن︎ّ︎َ︎ك︎ُ︎م︎ْ︎ ل︎َ︎ف︎ِ︎ے︎ ق︎َ︎و︎ْ︎ل︎ٖ︎ م︎ّ︎ُ︎خ︎ْ︎ت︎َ︎ل︎ِ︎ف︎ٖ︎ ٨︎",
      "numberInSurah": 8,
      "verse_key": "51:8"
    },
    {
      "text": "ي︎ُ︎و︎ف︎َ︎ك︎ُ︎ ع︎َ︎ن︎ْ︎ه︎ُ︎ م︎َ︎ن︎ُ︎ ا︎۟︎ف︎ِ︎ك︎َ︎ۖ︎ ٩︎",
      "numberInSurah": 9,
      "verse_key": "51:9"
    },
    {
      "text": "ق︎ُ︎ت︎ِ︎ل︎َ︎ ا︎َ︎۬︎ل︎ْ︎خ︎َ︎ر︎ّ︎َ︎ٰ︎ص︎ُ︎و︎ن︎َ︎ ١︎٠︎",
      "numberInSurah": 10,
      "verse_key": "51:10"
    },
    {
      "text": "ا︎َ︎۬︎ل︎ذ︎ِ︎ي︎ن︎َ︎ ه︎ُ︎م︎ْ︎ ف︎ِ︎ے︎ غ︎َ︎م︎ْ︎ر︎َ︎ة︎ٖ︎ س︎َ︎ا︎ه︎ُ︎و︎ن︎َ︎ۖ︎ ١︎١︎",
      "numberInSurah": 11,
      "verse_key": "51:11"
    },
    {
      "text": "ي︎َ︎س︎ْ︎ـ︎ٔ︎َ︎ل︎ُ︎و︎ن︎َ︎ أ︎َ︎ي︎ّ︎َ︎ا︎ن︎َ︎ ي︎َ︎و︎ْ︎م︎ُ︎ ا︎ُ︎۬︎ل︎د︎ّ︎ِ︎ي︎ن︎ِ︎ ١︎٢︎",
      "numberInSurah": 12,
      "verse_key": "51:12"
    },
    {
      "text": "ي︎َ︎و︎ْ︎م︎َ︎ ه︎ُ︎م︎ْ︎ ع︎َ︎ل︎َ︎ي︎ ا︎َ︎۬︎ل︎ن︎ّ︎۪︎ا︎ر︎ِ︎ ي︎ُ︎ف︎ْ︎ت︎َ︎ن︎ُ︎و︎ن︎َ︎ۖ︎ ١︎٣︎",
      "numberInSurah": 13,
      "verse_key": "51:13"
    },
    {
      "text": "ذ︎ُ︎و︎ق︎ُ︎و︎ا︎ْ︎ ف︎ِ︎ت︎ْ︎ن︎َ︎ت︎َ︎ك︎ُ︎م︎ْ︎ ه︎َ︎ٰ︎ذ︎َ︎ا︎ ا︎َ︎۬︎ل︎ذ︎ِ︎ے︎ ك︎ُ︎ن︎ت︎ُ︎م︎ ب︎ِ︎ه︎ِ︎ۦ︎ ت︎َ︎س︎ْ︎ت︎َ︎ع︎ْ︎ج︎ِ︎ل︎ُ︎و︎ن︎َ︎ۖ︎ ١︎٤︎",
      "numberInSurah": 14,
      "verse_key": "51:14"
    },
    {
      "text": "إ︎ِ︎ن︎ّ︎َ︎ ا︎َ︎۬︎ل︎ْ︎م︎ُ︎ت︎ّ︎َ︎ق︎ِ︎ي︎ن︎َ︎ ف︎ِ︎ے︎ ج︎َ︎ن︎ّ︎َ︎ٰ︎ت︎ٖ︎ و︎َ︎ع︎ُ︎ي︎ُ︎و︎ن︎ٍ︎ ١︎٥︎",
      "numberInSurah": 15,
      "verse_key": "51:15"
    },
    {
      "text": "ا︎ٰ︎خ︎ِ︎ذ︎ِ︎ي︎ن︎َ︎ م︎َ︎ا︎ٓ︎ ء︎َ︎ا︎ت︎۪︎ي︎ٰ︎ه︎ُ︎م︎ْ︎ ر︎َ︎ب︎ّ︎ُ︎ه︎ُ︎م︎ُ︎ۥ︎ٓ︎ۖ︎ إ︎ِ︎ن︎ّ︎َ︎ه︎ُ︎م︎ْ︎ ك︎َ︎ا︎ن︎ُ︎و︎ا︎ْ︎ ق︎َ︎ب︎ْ︎ل︎َ︎ ذ︎َ︎ٰ︎ل︎ِ︎ك︎َ︎ م︎ُ︎ح︎ْ︎س︎ِ︎ن︎ِ︎ي︎ن︎َ︎ۖ︎ ١︎٦︎",
      "numberInSurah": 16,
      "verse_key": "51:16"
    },
    {
      "text": "ك︎َ︎ا︎ن︎ُ︎و︎ا︎ْ︎ ق︎َ︎ل︎ِ︎ي︎ل︎ا︎ٗ︎ م︎ّ︎ِ︎ن︎َ︎ ا︎َ︎۬︎ل︎ي︎ْ︎ل︎ِ︎ م︎َ︎ا︎ ي︎َ︎ه︎ْ︎ج︎َ︎ع︎ُ︎و︎ن︎َ︎ۖ︎ ١︎٧︎",
      "numberInSurah": 17,
      "verse_key": "51:17"
    },
    {
      "text": "و︎َ︎ب︎ِ︎ا︎ل︎َ︎ا︎س︎ْ︎ح︎۪︎ا︎ر︎ِ︎ ه︎ُ︎م︎ْ︎ ي︎َ︎س︎ْ︎ت︎َ︎غ︎ْ︎ف︎ِ︎ر︎ُ︎و︎ن︎َ︎ۖ︎ ١︎٨︎",
      "numberInSurah": 18,
      "verse_key": "51:18"
    },
    {
      "text": "و︎َ︎ف︎ِ︎ے︎ٓ︎ أ︎َ︎م︎ْ︎و︎َ︎ٰ︎ل︎ِ︎ه︎ِ︎م︎ْ︎ ح︎َ︎ق︎ّ︎ٞ︎ ل︎ّ︎ِ︎ل︎س︎ّ︎َ︎ا︎ٓ︎ئ︎ِ︎ل︎ِ︎ و︎َ︎ا︎ل︎ْ︎م︎َ︎ح︎ْ︎ر︎ُ︎و︎م︎ِ︎ۖ︎ ١︎٩︎",
      "numberInSurah": 19,
      "verse_key": "51:19"
    },
    {
      "text": "و︎َ︎ف︎ِ︎ے︎ ا︎ِ︎۬︎ل︎َ︎ا︎ر︎ْ︎ض︎ِ︎ ء︎َ︎ا︎ي︎َ︎ٰ︎ت︎ٞ︎ ل︎ّ︎ِ︎ل︎ْ︎م︎ُ︎و︎ق︎ِ︎ن︎ِ︎ي︎ن︎َ︎ۖ︎ ٢︎٠︎",
      "numberInSurah": 20,
      "verse_key": "51:20"
    },
    {
      "text": "و︎َ︎ف︎ِ︎ے︎ٓ︎ أ︎َ︎ن︎ف︎ُ︎س︎ِ︎ك︎ُ︎م︎ُ︎ۥ︎ٓ︎ۖ︎ أ︎َ︎ف︎َ︎ل︎َ︎ا︎ ت︎ُ︎ب︎ْ︎ص︎ِ︎ر︎ُ︎و︎ن︎َ︎ۖ︎ ٢︎١︎",
      "numberInSurah": 21,
      "verse_key": "51:21"
    },
    {
      "text": "و︎َ︎ف︎ِ︎ے︎ ا︎ِ︎۬︎ل︎س︎ّ︎َ︎م︎َ︎ا︎ٓ︎ء︎ِ︎ ر︎ِ︎ز︎ْ︎ق︎ُ︎ك︎ُ︎م︎ْ︎ و︎َ︎م︎َ︎ا︎ ت︎ُ︎و︎ع︎َ︎د︎ُ︎و︎ن︎َ︎ ٢︎٢︎",
      "numberInSurah": 22,
      "verse_key": "51:22"
    },
    {
      "text": "ف︎َ︎و︎َ︎ر︎َ︎ب︎ّ︎ِ︎ ا︎ِ︎۬︎ل︎س︎ّ︎َ︎م︎َ︎ا︎ٓ︎ء︎ِ︎ و︎َ︎ا︎ل︎َ︎ا︎ر︎ْ︎ض︎ِ︎ إ︎ِ︎ن︎ّ︎َ︎ه︎ُ︎ۥ︎ ل︎َ︎ح︎َ︎ق︎ّ︎ٞ︎ م︎ّ︎ِ︎ث︎ْ︎ل︎َ︎ م︎َ︎ا︎ٓ︎ أ︎َ︎ن︎ّ︎َ︎ك︎ُ︎م︎ْ︎ ت︎َ︎ن︎ط︎ِ︎ق︎ُ︎و︎ن︎َ︎ۖ︎ ٢︎٣︎",
      "numberInSurah": 23,
      "verse_key": "51:23"
    },
    {
      "text": "ه︎َ︎ل︎َ︎ ا︎َ︎ت︎۪︎ي︎ٰ︎ك︎َ︎ ح︎َ︎د︎ِ︎ي︎ث︎ُ︎ ض︎َ︎ي︎ْ︎ف︎ِ︎ إ︎ِ︎ب︎ْ︎ر︎َ︎ٰ︎ه︎ِ︎ي︎م︎َ︎ ا︎َ︎۬︎ل︎ْ︎م︎ُ︎ك︎ْ︎ر︎َ︎م︎ِ︎ي︎ن︎َ︎ ٢︎٤︎",
      "numberInSurah": 24,
      "verse_key": "51:24"
    },
    {
      "text": "إ︎ِ︎ذ︎ْ︎ د︎َ︎خ︎َ︎ل︎ُ︎و︎ا︎ْ︎ ع︎َ︎ل︎َ︎ي︎ْ︎ه︎ِ︎ ف︎َ︎ق︎َ︎ا︎ل︎ُ︎و︎ا︎ْ︎ س︎َ︎ل︎َ︎ٰ︎م︎ا︎ٗ︎ۖ︎ ق︎َ︎ا︎ل︎َ︎ س︎َ︎ل︎َ︎ٰ︎م︎ٞ︎ۖ︎ ق︎َ︎و︎ْ︎م︎ٞ︎ م︎ّ︎ُ︎ن︎ك︎َ︎ر︎ُ︎و︎ن︎َ︎ۖ︎ ٢︎٥︎",
      "numberInSurah": 25,
      "verse_key": "51:25"
    },
    {
      "text": "ف︎َ︎ر︎َ︎ا︎غ︎َ︎ إ︎ِ︎ل︎َ︎ي︎ٰ︎ٓ︎ أ︎َ︎ه︎ْ︎ل︎ِ︎ه︎ِ︎ۦ︎ ف︎َ︎ج︎َ︎ا︎ٓ︎ء︎َ︎ ب︎ِ︎ع︎ِ︎ج︎ْ︎ل︎ٖ︎ س︎َ︎م︎ِ︎ي︎ن︎ٖ︎ ٢︎٦︎",
      "numberInSurah": 26,
      "verse_key": "51:26"
    },
    {
      "text": "ف︎َ︎ق︎َ︎ر︎ّ︎َ︎ب︎َ︎ه︎ُ︎ۥ︎ٓ︎ إ︎ِ︎ل︎َ︎ي︎ْ︎ه︎ِ︎م︎ْ︎ ق︎َ︎ا︎ل︎َ︎ أ︎َ︎ل︎َ︎ا︎ ت︎َ︎ا︎ك︎ُ︎ل︎ُ︎و︎ن︎َ︎ۖ︎ ٢︎٧︎",
      "numberInSurah": 27,
      "verse_key": "51:27"
    },
    {
      "text": "ف︎َ︎أ︎َ︎و︎ْ︎ج︎َ︎س︎َ︎ م︎ِ︎ن︎ْ︎ه︎ُ︎م︎ْ︎ خ︎ِ︎ي︎ف︎َ︎ة︎ٗ︎ۖ︎ ق︎َ︎ا︎ل︎ُ︎و︎ا︎ْ︎ ل︎َ︎ا︎ ت︎َ︎خ︎َ︎ف︎ْ︎ۖ︎ و︎َ︎ب︎َ︎ش︎ّ︎َ︎ر︎ُ︎و︎ه︎ُ︎ ب︎ِ︎غ︎ُ︎ل︎َ︎ٰ︎م︎ٍ︎ ع︎َ︎ل︎ِ︎ي︎م︎ٖ︎ۖ︎ ٢︎٨︎",
      "numberInSurah": 28,
      "verse_key": "51:28"
    },
    {
      "text": "ف︎َ︎أ︎َ︎ق︎ْ︎ب︎َ︎ل︎َ︎ت︎ِ︎ ا︎ِ︎۪︎م︎ْ︎ر︎َ︎أ︎َ︎ت︎ُ︎ه︎ُ︎ۥ︎ ف︎ِ︎ے︎ ص︎َ︎ر︎ّ︎َ︎ة︎ٖ︎ ف︎َ︎ص︎َ︎ك︎ّ︎َ︎ت︎ْ︎ و︎َ︎ج︎ْ︎ه︎َ︎ه︎َ︎ا︎ و︎َ︎ق︎َ︎ا︎ل︎َ︎ت︎ْ︎ ع︎َ︎ج︎ُ︎و︎ز︎ٌ︎ ع︎َ︎ق︎ِ︎ي︎م︎ٞ︎ۖ︎ ٢︎٩︎",
      "numberInSurah": 29,
      "verse_key": "51:29"
    },
    {
      "text": "ق︎َ︎ا︎ل︎ُ︎و︎ا︎ْ︎ ك︎َ︎ذ︎َ︎ٰ︎ل︎ِ︎ك︎ِ︎ ق︎َ︎ا︎ل︎َ︎ ر︎َ︎ب︎ّ︎ُ︎ك︎ِ︎ۖ︎ إ︎ِ︎ن︎ّ︎َ︎ه︎ُ︎ۥ︎ ه︎ُ︎و︎َ︎ ا︎َ︎۬︎ل︎ْ︎ح︎َ︎ك︎ِ︎ي︎م︎ُ︎ ا︎ُ︎۬︎ل︎ْ︎ع︎َ︎ل︎ِ︎ي︎م︎ُ︎ۖ︎ ٣︎٠︎",
      "numberInSurah": 30,
      "verse_key": "51:30"
    }
  ],
  "source": {
    "type": "warsh-quran-apk",
    "timestamp": "2026-04-27T01:25:23.063Z"
  }
}