{
  "pageNumber": 522,
  "riwayaId": "warsh",
  "ayahs": [
    {
      "text": "۞︎ق︎َ︎ا︎ل︎َ︎ ف︎َ︎م︎َ︎ا︎ خ︎َ︎ط︎ْ︎ب︎ُ︎ك︎ُ︎م︎ُ︎ۥ︎ٓ︎ أ︎َ︎ي︎ّ︎ُ︎ه︎َ︎ا︎ ا︎َ︎۬︎ل︎ْ︎م︎ُ︎ر︎ْ︎س︎َ︎ل︎ُ︎و︎ن︎َ︎ۖ︎ ٣︎١︎",
      "numberInSurah": 31,
      "verse_key": "51:31"
    },
    {
      "text": "ق︎َ︎ا︎ل︎ُ︎و︎ٓ︎ا︎ْ︎ إ︎ِ︎ن︎ّ︎َ︎ا︎ٓ︎ أ︎ُ︎ر︎ْ︎س︎ِ︎ل︎ْ︎ن︎َ︎ا︎ٓ︎ إ︎ِ︎ل︎َ︎ي︎ٰ︎ ق︎َ︎و︎ْ︎م︎ٖ︎ م︎ّ︎ُ︎ج︎ْ︎ر︎ِ︎م︎ِ︎ي︎ن︎َ︎ ٣︎٢︎",
      "numberInSurah": 32,
      "verse_key": "51:32"
    },
    {
      "text": "ل︎ِ︎ن︎ُ︎ر︎ْ︎س︎ِ︎ل︎َ︎ ع︎َ︎ل︎َ︎ي︎ْ︎ه︎ِ︎م︎ْ︎ ح︎ِ︎ج︎َ︎ا︎ر︎َ︎ة︎ٗ︎ م︎ّ︎ِ︎ن︎ ط︎ِ︎ي︎ن︎ٖ︎ ٣︎٣︎",
      "numberInSurah": 33,
      "verse_key": "51:33"
    },
    {
      "text": "م︎ّ︎ُ︎س︎َ︎و︎ّ︎َ︎م︎َ︎ة︎ً︎ ع︎ِ︎ن︎د︎َ︎ ر︎َ︎ب︎ّ︎ِ︎ك︎َ︎ ل︎ِ︎ل︎ْ︎م︎ُ︎س︎ْ︎ر︎ِ︎ف︎ِ︎ي︎ن︎َ︎ۖ︎ ٣︎٤︎",
      "numberInSurah": 34,
      "verse_key": "51:34"
    },
    {
      "text": "ف︎َ︎أ︎َ︎خ︎ْ︎ر︎َ︎ج︎ْ︎ن︎َ︎ا︎ م︎َ︎ن︎ ك︎َ︎ا︎ن︎َ︎ ف︎ِ︎ي︎ه︎َ︎ا︎ م︎ِ︎ن︎َ︎ ا︎َ︎۬︎ل︎ْ︎م︎ُ︎و︎م︎ِ︎ن︎ِ︎ي︎ن︎َ︎ ٣︎٥︎",
      "numberInSurah": 35,
      "verse_key": "51:35"
    },
    {
      "text": "ف︎َ︎م︎َ︎ا︎ و︎َ︎ج︎َ︎د︎ْ︎ن︎َ︎ا︎ ف︎ِ︎ي︎ه︎َ︎ا︎ غ︎َ︎ي︎ْ︎ر︎َ︎ ب︎َ︎ي︎ْ︎ت︎ٖ︎ م︎ّ︎ِ︎ن︎َ︎ ا︎َ︎۬︎ل︎ْ︎م︎ُ︎س︎ْ︎ل︎ِ︎م︎ِ︎ي︎ن︎َ︎ ٣︎٦︎",
      "numberInSurah": 36,
      "verse_key": "51:36"
    },
    {
      "text": "و︎َ︎ت︎َ︎ر︎َ︎ك︎ْ︎ن︎َ︎ا︎ ف︎ِ︎ي︎ه︎َ︎ا︎ٓ︎ ء︎َ︎ا︎ي︎َ︎ة︎ٗ︎ ل︎ّ︎ِ︎ل︎ذ︎ِ︎ي︎ن︎َ︎ ي︎َ︎خ︎َ︎ا︎ف︎ُ︎و︎ن︎َ︎ ا︎َ︎۬︎ل︎ْ︎ع︎َ︎ذ︎َ︎ا︎ب︎َ︎ ا︎َ︎۬︎ل︎َ︎ا︎ل︎ِ︎ي︎م︎َ︎ۖ︎ ٣︎٧︎",
      "numberInSurah": 37,
      "verse_key": "51:37"
    },
    {
      "text": "و︎َ︎ف︎ِ︎ے︎ م︎ُ︎و︎س︎۪︎ي︎ٰ︎ٓ︎ إ︎ِ︎ذ︎َ︎ ا︎َ︎ر︎ْ︎س︎َ︎ل︎ْ︎ن︎َ︎ٰ︎ه︎ُ︎ إ︎ِ︎ل︎َ︎ي︎ٰ︎ ف︎ِ︎ر︎ْ︎ع︎َ︎و︎ْ︎ن︎َ︎ ب︎ِ︎س︎ُ︎ل︎ْ︎ط︎َ︎ٰ︎ن︎ٖ︎ م︎ّ︎ُ︎ب︎ِ︎ي︎ن︎ٖ︎ ٣︎٨︎",
      "numberInSurah": 38,
      "verse_key": "51:38"
    },
    {
      "text": "ف︎َ︎ت︎َ︎و︎َ︎ل︎ّ︎۪︎ي︎ٰ︎ ب︎ِ︎ر︎ُ︎ك︎ْ︎ن︎ِ︎ه︎ِ︎ۦ︎ و︎َ︎ق︎َ︎ا︎ل︎َ︎ س︎َ︎ٰ︎ح︎ِ︎ر︎ٌ︎ ا︎َ︎و︎ْ︎ م︎َ︎ج︎ْ︎ن︎ُ︎و︎ن︎ٞ︎ۖ︎ ٣︎٩︎",
      "numberInSurah": 39,
      "verse_key": "51:39"
    },
    {
      "text": "ف︎َ︎أ︎َ︎خ︎َ︎ذ︎ْ︎ن︎َ︎ٰ︎ه︎ُ︎ و︎َ︎ج︎ُ︎ن︎ُ︎و︎د︎َ︎ه︎ُ︎ۥ︎ ف︎َ︎ن︎َ︎ب︎َ︎ذ︎ْ︎ن︎َ︎ٰ︎ه︎ُ︎م︎ْ︎ ف︎ِ︎ے︎ ا︎ِ︎۬︎ل︎ْ︎ي︎َ︎م︎ّ︎ِ︎ و︎َ︎ه︎ُ︎و︎َ︎ م︎ُ︎ل︎ِ︎ي︎م︎ٞ︎ۖ︎ ٤︎٠︎",
      "numberInSurah": 40,
      "verse_key": "51:40"
    },
    {
      "text": "و︎َ︎ف︎ِ︎ے︎ ع︎َ︎ا︎د︎ٍ︎ ا︎ِ︎ذ︎َ︎ ا︎َ︎ر︎ْ︎س︎َ︎ل︎ْ︎ن︎َ︎ا︎ ع︎َ︎ل︎َ︎ي︎ْ︎ه︎ِ︎م︎ُ︎ ا︎ُ︎۬︎ل︎ر︎ّ︎ِ︎ي︎ح︎َ︎ ا︎َ︎۬︎ل︎ْ︎ع︎َ︎ق︎ِ︎ي︎م︎َ︎ ٤︎١︎",
      "numberInSurah": 41,
      "verse_key": "51:41"
    },
    {
      "text": "م︎َ︎ا︎ ت︎َ︎ذ︎َ︎ر︎ُ︎ م︎ِ︎ن︎ ش︎َ︎ے︎ْ︎ء︎ٍ︎ ا︎َ︎ت︎َ︎ت︎ْ︎ ع︎َ︎ل︎َ︎ي︎ْ︎ه︎ِ︎ إ︎ِ︎ل︎ّ︎َ︎ا︎ ج︎َ︎ع︎َ︎ل︎َ︎ت︎ْ︎ه︎ُ︎ ك︎َ︎ا︎ل︎ر︎ّ︎َ︎م︎ِ︎ي︎م︎ِ︎ۖ︎ ٤︎٢︎",
      "numberInSurah": 42,
      "verse_key": "51:42"
    },
    {
      "text": "و︎َ︎ف︎ِ︎ے︎ ث︎َ︎م︎ُ︎و︎د︎َ︎ إ︎ِ︎ذ︎ْ︎ ق︎ِ︎ي︎ل︎َ︎ ل︎َ︎ه︎ُ︎م︎ْ︎ ت︎َ︎م︎َ︎ت︎ّ︎َ︎ع︎ُ︎و︎ا︎ْ︎ ح︎َ︎ت︎ّ︎َ︎ي︎ٰ︎ ح︎ِ︎ي︎ن︎ٖ︎ ٤︎٣︎",
      "numberInSurah": 43,
      "verse_key": "51:43"
    },
    {
      "text": "ف︎َ︎ع︎َ︎ت︎َ︎و︎ْ︎ا︎ْ︎ ع︎َ︎ن︎َ︎ ا︎َ︎م︎ْ︎ر︎ِ︎ ر︎َ︎ب︎ّ︎ِ︎ه︎ِ︎م︎ْ︎ ف︎َ︎أ︎َ︎خ︎َ︎ذ︎َ︎ت︎ْ︎ه︎ُ︎م︎ُ︎ ا︎ُ︎۬︎ل︎ص︎ّ︎َ︎ٰ︎ع︎ِ︎ق︎َ︎ة︎ُ︎ و︎َ︎ه︎ُ︎م︎ْ︎ ي︎َ︎ن︎ظ︎ُ︎ر︎ُ︎و︎ن︎َ︎ۖ︎ ٤︎٤︎",
      "numberInSurah": 44,
      "verse_key": "51:44"
    },
    {
      "text": "ف︎َ︎م︎َ︎ا︎ ا︎َ︎۪︎س︎ْ︎ت︎َ︎ط︎َ︎ٰ︎ع︎ُ︎و︎ا︎ْ︎ م︎ِ︎ن︎ ق︎ِ︎ي︎َ︎ا︎م︎ٖ︎ و︎َ︎م︎َ︎ا︎ ك︎َ︎ا︎ن︎ُ︎و︎ا︎ْ︎ م︎ُ︎ن︎ت︎َ︎ص︎ِ︎ر︎ِ︎ي︎ن︎َ︎ۖ︎ ٤︎٥︎",
      "numberInSurah": 45,
      "verse_key": "51:45"
    },
    {
      "text": "و︎َ︎ق︎َ︎و︎ْ︎م︎َ︎ ن︎ُ︎و︎ح︎ٖ︎ م︎ّ︎ِ︎ن︎ ق︎َ︎ب︎ْ︎ل︎ُ︎ۖ︎ إ︎ِ︎ن︎ّ︎َ︎ه︎ُ︎م︎ْ︎ ك︎َ︎ا︎ن︎ُ︎و︎ا︎ْ︎ ق︎َ︎و︎ْ︎م︎ا︎ٗ︎ ف︎َ︎ٰ︎س︎ِ︎ق︎ِ︎ي︎ن︎َ︎ۖ︎ ٤︎٦︎",
      "numberInSurah": 46,
      "verse_key": "51:46"
    },
    {
      "text": "و︎َ︎ا︎ل︎س︎ّ︎َ︎م︎َ︎ا︎ٓ︎ء︎َ︎ ب︎َ︎ن︎َ︎ي︎ْ︎ن︎َ︎ٰ︎ه︎َ︎ا︎ ب︎ِ︎أ︎َ︎ي︎َ︎ي︎ْ︎د︎ٖ︎ۖ︎ و︎َ︎إ︎ِ︎ن︎ّ︎َ︎ا︎ ل︎َ︎م︎ُ︎و︎س︎ِ︎ع︎ُ︎و︎ن︎َ︎ۖ︎ ٤︎٧︎",
      "numberInSurah": 47,
      "verse_key": "51:47"
    },
    {
      "text": "و︎َ︎ا︎ل︎َ︎ا︎ر︎ْ︎ض︎َ︎ ف︎َ︎ر︎َ︎ش︎ْ︎ن︎َ︎ٰ︎ه︎َ︎ا︎ ف︎َ︎ن︎ِ︎ع︎ْ︎م︎َ︎ ا︎َ︎۬︎ل︎ْ︎م︎َ︎ٰ︎ه︎ِ︎د︎ُ︎و︎ن︎َ︎ۖ︎ ٤︎٨︎",
      "numberInSurah": 48,
      "verse_key": "51:48"
    },
    {
      "text": "و︎َ︎م︎ِ︎ن︎ ك︎ُ︎ل︎ّ︎ِ︎ ش︎َ︎ے︎ْ︎ء︎ٍ︎ خ︎َ︎ل︎َ︎ق︎ْ︎ن︎َ︎ا︎ ز︎َ︎و︎ْ︎ج︎َ︎ي︎ْ︎ن︎ِ︎ ل︎َ︎ع︎َ︎ل︎ّ︎َ︎ك︎ُ︎م︎ْ︎ ت︎َ︎ذ︎ّ︎َ︎ك︎ّ︎َ︎ر︎ُ︎و︎ن︎َ︎ۖ︎ ٤︎٩︎",
      "numberInSurah": 49,
      "verse_key": "51:49"
    },
    {
      "text": "ف︎َ︎ف︎ِ︎ر︎ّ︎ُ︎و︎ٓ︎ا︎ْ︎ إ︎ِ︎ل︎َ︎ي︎ ا︎َ︎۬︎ل︎ل︎ّ︎َ︎ه︎ِ︎ إ︎ِ︎ن︎ّ︎ِ︎ے︎ ل︎َ︎ك︎ُ︎م︎ م︎ّ︎ِ︎ن︎ْ︎ه︎ُ︎ ن︎َ︎ذ︎ِ︎ي︎ر︎ٞ︎ م︎ّ︎ُ︎ب︎ِ︎ي︎ن︎ٞ︎ۖ︎ ٥︎٠︎",
      "numberInSurah": 50,
      "verse_key": "51:50"
    },
    {
      "text": "و︎َ︎ل︎َ︎ا︎ ت︎َ︎ج︎ْ︎ع︎َ︎ل︎ُ︎و︎ا︎ْ︎ م︎َ︎ع︎َ︎ ا︎َ︎۬︎ل︎ل︎ّ︎َ︎ه︎ِ︎ إ︎ِ︎ل︎َ︎ٰ︎ه︎ا︎ً︎ ا︎ٰ︎خ︎َ︎ر︎َ︎ إ︎ِ︎ن︎ّ︎ِ︎ے︎ ل︎َ︎ك︎ُ︎م︎ م︎ّ︎ِ︎ن︎ْ︎ه︎ُ︎ ن︎َ︎ذ︎ِ︎ي︎ر︎ٞ︎ م︎ّ︎ُ︎ب︎ِ︎ي︎ن︎ٞ︎ۖ︎ ٥︎١︎",
      "numberInSurah": 51,
      "verse_key": "51:51"
    }
  ],
  "source": {
    "type": "warsh-quran-apk",
    "timestamp": "2026-04-27T01:25:23.052Z"
  }
}