{
  "pageNumber": 110,
  "riwayaId": "warsh",
  "ayahs": [
    {
      "text": "ف︎َ︎ب︎ِ︎م︎َ︎ا︎ ن︎َ︎ق︎ْ︎ض︎ِ︎ه︎ِ︎م︎ م︎ّ︎ِ︎ي︎ث︎َ︎ٰ︎ق︎َ︎ه︎ُ︎م︎ْ︎ ل︎َ︎ع︎َ︎ن︎ّ︎َ︎ٰ︎ه︎ُ︎م︎ْ︎ و︎َ︎ج︎َ︎ع︎َ︎ل︎ْ︎ن︎َ︎ا︎ ق︎ُ︎ل︎ُ︎و︎ب︎َ︎ه︎ُ︎م︎ْ︎ ق︎َ︎ٰ︎س︎ِ︎ي︎َ︎ة︎ٗ︎ ي︎ُ︎ح︎َ︎ر︎ّ︎ِ︎ف︎ُ︎و︎ن︎َ︎ ا︎َ︎۬︎ل︎ْ︎ك︎َ︎ل︎ِ︎م︎َ︎ ع︎َ︎ن︎ م︎ّ︎َ︎و︎َ︎ا︎ض︎ِ︎ع︎ِ︎ه︎ِ︎ۦ︎ و︎َ︎ن︎َ︎س︎ُ︎و︎ا︎ْ︎ ح︎َ︎ظ︎ّ︎ا︎ٗ︎ م︎ّ︎ِ︎م︎ّ︎َ︎ا︎ ذ︎ُ︎ك︎ّ︎ِ︎ر︎ُ︎و︎ا︎ْ︎ ب︎ِ︎ه︎ِ︎ۦ︎ۖ︎ و︎َ︎ل︎َ︎ا︎ ت︎َ︎ز︎َ︎ا︎ل︎ُ︎ ت︎َ︎ط︎ّ︎َ︎ل︎ِ︎ع︎ُ︎ ع︎َ︎ل︎َ︎ي︎ٰ︎ خ︎َ︎ا︎ٓ︎ئ︎ِ︎ن︎َ︎ة︎ٖ︎ م︎ّ︎ِ︎ن︎ْ︎ه︎ُ︎م︎ُ︎ۥ︎ٓ︎ إ︎ِ︎ل︎ّ︎َ︎ا︎ ق︎َ︎ل︎ِ︎ي︎ل︎ا︎ٗ︎ م︎ّ︎ِ︎ن︎ْ︎ه︎ُ︎م︎ْ︎ۖ︎ ف︎َ︎ا︎ع︎ْ︎ف︎ُ︎ ع︎َ︎ن︎ْ︎ه︎ُ︎م︎ْ︎ و︎َ︎ا︎ص︎ْ︎ف︎َ︎ح︎ِ︎ۖ︎ ا︎ِ︎ن︎ّ︎َ︎ ا︎َ︎۬︎ل︎ل︎ّ︎َ︎ه︎َ︎ ي︎ُ︎ح︎ِ︎ب︎ّ︎ُ︎ ا︎ُ︎۬︎ل︎ْ︎م︎ُ︎ح︎ْ︎س︎ِ︎ن︎ِ︎ي︎ن︎َ︎ۖ︎ ١︎٤︎",
      "numberInSurah": 14,
      "verse_key": "5:14"
    },
    {
      "text": "و︎َ︎م︎ِ︎ن︎َ︎ ا︎َ︎۬︎ل︎ذ︎ِ︎ي︎ن︎َ︎ ق︎َ︎ا︎ل︎ُ︎و︎ٓ︎ا︎ْ︎ إ︎ِ︎ن︎ّ︎َ︎ا︎ ن︎َ︎ص︎َ︎ٰ︎ر︎۪︎ي︎ٰ︎ٓ︎ أ︎َ︎خ︎َ︎ذ︎ْ︎ن︎َ︎ا︎ م︎ِ︎ي︎ث︎َ︎ٰ︎ق︎َ︎ه︎ُ︎م︎ْ︎ ف︎َ︎ن︎َ︎س︎ُ︎و︎ا︎ْ︎ ح︎َ︎ظ︎ّ︎ا︎ٗ︎ م︎ّ︎ِ︎م︎ّ︎َ︎ا︎ ذ︎ُ︎ك︎ّ︎ِ︎ر︎ُ︎و︎ا︎ْ︎ ب︎ِ︎ه︎ِ︎ۦ︎ ف︎َ︎أ︎َ︎غ︎ْ︎ر︎َ︎ي︎ْ︎ن︎َ︎ا︎ ب︎َ︎ي︎ْ︎ن︎َ︎ه︎ُ︎م︎ُ︎ ا︎ُ︎۬︎ل︎ْ︎ع︎َ︎د︎َ︎ٰ︎و︎َ︎ة︎َ︎ و︎َ︎ا︎ل︎ْ︎ب︎َ︎غ︎ْ︎ض︎َ︎ا︎ٓ︎ء︎َ︎ ا︎۪︎ل︎َ︎ي︎ٰ︎ ي︎َ︎و︎ْ︎م︎ِ︎ ا︎ِ︎۬︎ل︎ْ︎ق︎ِ︎ي︎َ︎ٰ︎م︎َ︎ة︎ِ︎ۖ︎ و︎َ︎س︎َ︎و︎ْ︎ف︎َ︎ ي︎ُ︎ن︎َ︎ب︎ّ︎ِ︎ي︎ٔ︎ُ︎ه︎ُ︎م︎ُ︎ ا︎ُ︎۬︎ل︎ل︎ّ︎َ︎ه︎ُ︎ ب︎ِ︎م︎َ︎ا︎ ك︎َ︎ا︎ن︎ُ︎و︎ا︎ْ︎ ي︎َ︎ص︎ْ︎ن︎َ︎ع︎ُ︎و︎ن︎َ︎ۖ︎ ١︎٥︎",
      "numberInSurah": 15,
      "verse_key": "5:15"
    },
    {
      "text": "ي︎َ︎ٰ︎ٓ︎أ︎َ︎ه︎ْ︎ل︎َ︎ ا︎َ︎۬︎ل︎ْ︎ك︎ِ︎ت︎َ︎ٰ︎ب︎ِ︎ ق︎َ︎د︎ْ︎ ج︎َ︎ا︎ٓ︎ء︎َ︎ك︎ُ︎م︎ْ︎ ر︎َ︎س︎ُ︎و︎ل︎ُ︎ن︎َ︎ا︎ ي︎ُ︎ب︎َ︎ي︎ّ︎ِ︎ن︎ُ︎ ل︎َ︎ك︎ُ︎م︎ْ︎ ك︎َ︎ث︎ِ︎ي︎ر︎ا︎ٗ︎ م︎ّ︎ِ︎م︎ّ︎َ︎ا︎ ك︎ُ︎ن︎ت︎ُ︎م︎ْ︎ ت︎ُ︎خ︎ْ︎ف︎ُ︎و︎ن︎َ︎ م︎ِ︎ن︎َ︎ ا︎َ︎۬︎ل︎ْ︎ك︎ِ︎ت︎َ︎ٰ︎ب︎ِ︎ و︎َ︎ي︎َ︎ع︎ْ︎ف︎ُ︎و︎ا︎ْ︎ ع︎َ︎ن︎ ك︎َ︎ث︎ِ︎ي︎ر︎ٖ︎ۖ︎ ١︎٦︎",
      "numberInSurah": 16,
      "verse_key": "5:16"
    },
    {
      "text": "ق︎َ︎د︎ْ︎ ج︎َ︎ا︎ٓ︎ء︎َ︎ك︎ُ︎م︎ م︎ّ︎ِ︎ن︎َ︎ ا︎َ︎۬︎ل︎ل︎ّ︎َ︎ه︎ِ︎ ن︎ُ︎و︎ر︎ٞ︎ و︎َ︎ك︎ِ︎ت︎َ︎ٰ︎ب︎ٞ︎ م︎ّ︎ُ︎ب︎ِ︎ي︎ن︎ٞ︎ ١︎٧︎",
      "numberInSurah": 17,
      "verse_key": "5:17"
    }
  ],
  "source": {
    "type": "warsh-quran-apk",
    "timestamp": "2026-04-27T01:24:41.171Z"
  }
}