{
  "pageNumber": 540,
  "riwayaId": "warsh",
  "ayahs": [
    {
      "text": "ا︎ِ︎۪︎ع︎ْ︎ل︎َ︎م︎ُ︎و︎ٓ︎ا︎ْ︎ أ︎َ︎ن︎ّ︎َ︎م︎َ︎ا︎ ا︎َ︎۬︎ل︎ْ︎ح︎َ︎ي︎َ︎و︎ٰ︎ة︎ُ︎ ا︎ُ︎۬︎ل︎د︎ّ︎ُ︎ن︎ْ︎ي︎۪︎ا︎ ل︎َ︎ع︎ِ︎ب︎ٞ︎ و︎َ︎ل︎َ︎ه︎ْ︎و︎ٞ︎ و︎َ︎ز︎ِ︎ي︎ن︎َ︎ة︎ٞ︎ و︎َ︎ت︎َ︎ف︎َ︎ا︎خ︎ُ︎ر︎ُ︎ۢ︎ ب︎َ︎ي︎ْ︎ن︎َ︎ك︎ُ︎م︎ْ︎ و︎َ︎ت︎َ︎ك︎َ︎ا︎ث︎ُ︎ر︎ٞ︎ ف︎ِ︎ے︎ ا︎ِ︎۬︎ل︎َ︎ا︎م︎ْ︎و︎َ︎ٰ︎ل︎ِ︎ و︎َ︎ا︎ل︎َ︎ا︎و︎ْ︎ل︎َ︎ٰ︎د︎ِ︎ ك︎َ︎م︎َ︎ث︎َ︎ل︎ِ︎ غ︎َ︎ي︎ْ︎ث︎ٍ︎ ا︎َ︎ع︎ْ︎ج︎َ︎ب︎َ︎ ا︎َ︎۬︎ل︎ْ︎ك︎ُ︎ف︎ّ︎َ︎ا︎ر︎َ︎ ن︎َ︎ب︎َ︎ا︎ت︎ُ︎ه︎ُ︎ۥ︎ ث︎ُ︎م︎ّ︎َ︎ ي︎َ︎ه︎ِ︎ي︎ج︎ُ︎ ف︎َ︎ت︎َ︎ر︎۪︎ي︎ٰ︎ه︎ُ︎ م︎ُ︎ص︎ْ︎ف︎َ︎ر︎ّ︎ا︎ٗ︎ ث︎ُ︎م︎ّ︎َ︎ ي︎َ︎ك︎ُ︎و︎ن︎ُ︎ ح︎ُ︎ط︎َ︎ٰ︎م︎ا︎ٗ︎ۖ︎ و︎َ︎ف︎ِ︎ے︎ ا︎ِ︎۬︎ل︎َ︎ا︎خ︎ِ︎ر︎َ︎ة︎ِ︎ ع︎َ︎ذ︎َ︎ا︎ب︎ٞ︎ ش︎َ︎د︎ِ︎ي︎د︎ٞ︎ و︎َ︎م︎َ︎غ︎ْ︎ف︎ِ︎ر︎َ︎ة︎ٞ︎ م︎ّ︎ِ︎ن︎َ︎ ا︎َ︎۬︎ل︎ل︎ّ︎َ︎ه︎ِ︎ و︎َ︎ر︎ِ︎ض︎ْ︎و︎َ︎ٰ︎ن︎ٞ︎ۖ︎ و︎َ︎م︎َ︎ا︎ ا︎َ︎۬︎ل︎ْ︎ح︎َ︎ي︎َ︎و︎ٰ︎ة︎ُ︎ ا︎ُ︎۬︎ل︎د︎ّ︎ُ︎ن︎ْ︎ي︎۪︎ا︎ٓ︎ إ︎ِ︎ل︎ّ︎َ︎ا︎ م︎َ︎ت︎َ︎ٰ︎ع︎ُ︎ ا︎ُ︎۬︎ل︎ْ︎غ︎ُ︎ر︎ُ︎و︎ر︎ِ︎ۖ︎ ١︎٩︎",
      "numberInSurah": 19,
      "verse_key": "57:19"
    },
    {
      "text": "س︎َ︎ا︎ب︎ِ︎ق︎ُ︎و︎ٓ︎ا︎ْ︎ إ︎ِ︎ل︎َ︎ي︎ٰ︎ م︎َ︎غ︎ْ︎ف︎ِ︎ر︎َ︎ة︎ٖ︎ م︎ّ︎ِ︎ن︎ ر︎ّ︎َ︎ب︎ّ︎ِ︎ك︎ُ︎م︎ْ︎ و︎َ︎ج︎َ︎ن︎ّ︎َ︎ة︎ٍ︎ ع︎َ︎ر︎ْ︎ض︎ُ︎ه︎َ︎ا︎ ك︎َ︎ع︎َ︎ر︎ْ︎ض︎ِ︎ ا︎ِ︎۬︎ل︎س︎ّ︎َ︎م︎َ︎ا︎ٓ︎ء︎ِ︎ و︎َ︎ا︎ل︎َ︎ا︎ر︎ْ︎ض︎ِ︎ أ︎ُ︎ع︎ِ︎د︎ّ︎َ︎ت︎ْ︎ ل︎ِ︎ل︎ذ︎ِ︎ي︎ن︎َ︎ ء︎َ︎ا︎م︎َ︎ن︎ُ︎و︎ا︎ْ︎ ب︎ِ︎ا︎ل︎ل︎ّ︎َ︎ه︎ِ︎ و︎َ︎ر︎ُ︎س︎ُ︎ل︎ِ︎ه︎ِ︎ۦ︎ۖ︎ ذ︎َ︎ٰ︎ل︎ِ︎ك︎َ︎ ف︎َ︎ض︎ْ︎ل︎ُ︎ ا︎ُ︎۬︎ل︎ل︎ّ︎َ︎ه︎ِ︎ ي︎ُ︎و︎ت︎ِ︎ي︎ه︎ِ︎ م︎َ︎ن︎ْ︎ ي︎ّ︎َ︎ش︎َ︎ا︎ٓ︎ء︎ُ︎ۖ︎ و︎َ︎ا︎ل︎ل︎ّ︎َ︎ه︎ُ︎ ذ︎ُ︎و︎ ا︎ُ︎۬︎ل︎ْ︎ف︎َ︎ض︎ْ︎ل︎ِ︎ ا︎ِ︎۬︎ل︎ْ︎ع︎َ︎ظ︎ِ︎ي︎م︎ِ︎ۖ︎ ٢︎٠︎",
      "numberInSurah": 20,
      "verse_key": "57:20"
    },
    {
      "text": "۞︎م︎َ︎ا︎ٓ︎ أ︎َ︎ص︎َ︎ا︎ب︎َ︎ م︎ِ︎ن︎ م︎ّ︎ُ︎ص︎ِ︎ي︎ب︎َ︎ة︎ٖ︎ ف︎ِ︎ے︎ ا︎ِ︎۬︎ل︎َ︎ا︎ر︎ْ︎ض︎ِ︎ و︎َ︎ل︎َ︎ا︎ ف︎ِ︎ے︎ٓ︎ أ︎َ︎ن︎ف︎ُ︎س︎ِ︎ك︎ُ︎م︎ُ︎ۥ︎ٓ︎ إ︎ِ︎ل︎ّ︎َ︎ا︎ ف︎ِ︎ے︎ ك︎ِ︎ت︎َ︎ٰ︎ب︎ٖ︎ م︎ّ︎ِ︎ن︎ ق︎َ︎ب︎ْ︎ل︎ِ︎ أ︎َ︎ن︎ ن︎ّ︎َ︎ب︎ْ︎ر︎َ︎أ︎َ︎ه︎َ︎ا︎ٓ︎ۖ︎ إ︎ِ︎ن︎ّ︎َ︎ ذ︎َ︎ٰ︎ل︎ِ︎ك︎َ︎ ع︎َ︎ل︎َ︎ي︎ ا︎َ︎۬︎ل︎ل︎ّ︎َ︎ه︎ِ︎ ي︎َ︎س︎ِ︎ي︎ر︎ٞ︎ ٢︎١︎",
      "numberInSurah": 21,
      "verse_key": "57:21"
    },
    {
      "text": "ل︎ّ︎ِ︎ك︎َ︎ي︎ْ︎ل︎َ︎ا︎ ت︎َ︎ا︎س︎َ︎و︎ْ︎ا︎ْ︎ ع︎َ︎ل︎َ︎ي︎ٰ︎ م︎َ︎ا︎ ف︎َ︎ا︎ت︎َ︎ك︎ُ︎م︎ْ︎ و︎َ︎ل︎َ︎ا︎ ت︎َ︎ف︎ْ︎ر︎َ︎ح︎ُ︎و︎ا︎ْ︎ ب︎ِ︎م︎َ︎ا︎ٓ︎ ء︎َ︎ا︎ت︎۪︎ي︎ٰ︎ك︎ُ︎م︎ْ︎ۖ︎ و︎َ︎ا︎ل︎ل︎ّ︎َ︎ه︎ُ︎ ل︎َ︎ا︎ ي︎ُ︎ح︎ِ︎ب︎ّ︎ُ︎ ك︎ُ︎ل︎ّ︎َ︎ م︎ُ︎خ︎ْ︎ت︎َ︎ا︎ل︎ٖ︎ ف︎َ︎خ︎ُ︎و︎ر︎ٍ︎ۖ︎ ٢︎٢︎",
      "numberInSurah": 22,
      "verse_key": "57:22"
    },
    {
      "text": "ا︎ِ︎۬︎ل︎ذ︎ِ︎ي︎ن︎َ︎ ي︎َ︎ب︎ْ︎خ︎َ︎ل︎ُ︎و︎ن︎َ︎ و︎َ︎ي︎َ︎ا︎م︎ُ︎ر︎ُ︎و︎ن︎َ︎ ا︎َ︎۬︎ل︎ن︎ّ︎َ︎ا︎س︎َ︎ ب︎ِ︎ا︎ل︎ْ︎ب︎ُ︎خ︎ْ︎ل︎ِ︎ۖ︎ و︎َ︎م︎َ︎ن︎ْ︎ ي︎ّ︎َ︎ت︎َ︎و︎َ︎ل︎ّ︎َ︎ ف︎َ︎إ︎ِ︎ن︎ّ︎َ︎ ا︎َ︎۬︎ل︎ل︎ّ︎َ︎ه︎َ︎ ا︎َ︎۬︎ل︎ْ︎غ︎َ︎ن︎ِ︎ي︎ّ︎ُ︎ ا︎ُ︎۬︎ل︎ْ︎ح︎َ︎م︎ِ︎ي︎د︎ُ︎ۖ︎ ٢︎٣︎",
      "numberInSurah": 23,
      "verse_key": "57:23"
    },
    {
      "text": "ل︎َ︎ق︎َ︎د︎َ︎ ا︎َ︎ر︎ْ︎س︎َ︎ل︎ْ︎ن︎َ︎ا︎ ر︎ُ︎س︎ُ︎ل︎َ︎ن︎َ︎ا︎ ب︎ِ︎ا︎ل︎ْ︎ب︎َ︎ي︎ّ︎ِ︎ن︎َ︎ٰ︎ت︎ِ︎ و︎َ︎أ︎َ︎ن︎ز︎َ︎ل︎ْ︎ن︎َ︎ا︎ م︎َ︎ع︎َ︎ه︎ُ︎م︎ُ︎ ا︎ُ︎۬︎ل︎ْ︎ك︎ِ︎ت︎َ︎ٰ︎ب︎َ︎ و︎َ︎ا︎ل︎ْ︎م︎ِ︎ي︎ز︎َ︎ا︎ن︎َ︎ ل︎ِ︎ي︎َ︎ق︎ُ︎و︎م︎َ︎ ا︎َ︎۬︎ل︎ن︎ّ︎َ︎ا︎س︎ُ︎ ب︎ِ︎ا︎ل︎ْ︎ق︎ِ︎س︎ْ︎ط︎ِ︎ۖ︎ و︎َ︎أ︎َ︎ن︎ز︎َ︎ل︎ْ︎ن︎َ︎ا︎ ا︎َ︎۬︎ل︎ْ︎ح︎َ︎د︎ِ︎ي︎د︎َ︎ ف︎ِ︎ي︎ه︎ِ︎ ب︎َ︎أ︎ْ︎س︎ٞ︎ ش︎َ︎د︎ِ︎ي︎د︎ٞ︎ و︎َ︎م︎َ︎ن︎َ︎ٰ︎ف︎ِ︎ع︎ُ︎ ل︎ِ︎ل︎ن︎ّ︎َ︎ا︎س︎ِ︎ و︎َ︎ل︎ِ︎ي︎َ︎ع︎ْ︎ل︎َ︎م︎َ︎ ا︎َ︎۬︎ل︎ل︎ّ︎َ︎ه︎ُ︎ م︎َ︎ن︎ْ︎ ي︎ّ︎َ︎ن︎ص︎ُ︎ر︎ُ︎ه︎ُ︎ۥ︎ و︎َ︎ر︎ُ︎س︎ُ︎ل︎َ︎ه︎ُ︎ۥ︎ ب︎ِ︎ا︎ل︎ْ︎غ︎َ︎ي︎ْ︎ب︎ِ︎ۖ︎ إ︎ِ︎ن︎ّ︎َ︎ ا︎َ︎۬︎ل︎ل︎ّ︎َ︎ه︎َ︎ ق︎َ︎و︎ِ︎ي︎ّ︎ٌ︎ ع︎َ︎ز︎ِ︎ي︎ز︎ٞ︎ۖ︎ ٢︎٤︎",
      "numberInSurah": 24,
      "verse_key": "57:24"
    }
  ],
  "source": {
    "type": "warsh-quran-apk",
    "timestamp": "2026-04-27T01:25:24.009Z"
  }
}