{
  "pageNumber": 420,
  "riwayaId": "warsh",
  "ayahs": [
    {
      "text": "ق︎ُ︎ل︎ ل︎ّ︎َ︎ن︎ْ︎ ي︎ّ︎َ︎ن︎ف︎َ︎ع︎َ︎ك︎ُ︎م︎ُ︎ ا︎ُ︎۬︎ل︎ْ︎ف︎ِ︎ر︎َ︎ا︎ر︎ُ︎ إ︎ِ︎ن︎ ف︎َ︎ر︎َ︎ر︎ْ︎ت︎ُ︎م︎ م︎ّ︎ِ︎ن︎َ︎ ا︎َ︎۬︎ل︎ْ︎م︎َ︎و︎ْ︎ت︎ِ︎ أ︎َ︎و︎ِ︎ ا︎ِ︎۬︎ل︎ْ︎ق︎َ︎ت︎ْ︎ل︎ِ︎ و︎َ︎إ︎ِ︎ذ︎ا︎ٗ︎ ل︎ّ︎َ︎ا︎ ت︎ُ︎م︎َ︎ت︎ّ︎َ︎ع︎ُ︎و︎ن︎َ︎ إ︎ِ︎ل︎ّ︎َ︎ا︎ ق︎َ︎ل︎ِ︎ي︎ل︎ا︎ٗ︎ۖ︎ ١︎٦︎",
      "numberInSurah": 16,
      "verse_key": "33:16"
    },
    {
      "text": "ق︎ُ︎ل︎ْ︎ م︎َ︎ن︎ ذ︎َ︎ا︎ ا︎َ︎۬︎ل︎ذ︎ِ︎ے︎ ي︎َ︎ع︎ْ︎ص︎ِ︎م︎ُ︎ك︎ُ︎م︎ م︎ّ︎ِ︎ن︎َ︎ ا︎َ︎۬︎ل︎ل︎ّ︎َ︎ه︎ِ︎ إ︎ِ︎ن︎َ︎ ا︎َ︎ر︎َ︎ا︎د︎َ︎ ب︎ِ︎ك︎ُ︎م︎ْ︎ س︎ُ︎و︎ٓ︎ء︎ا︎ً︎ ا︎َ︎و︎َ︎ ا︎َ︎ر︎َ︎ا︎د︎َ︎ ب︎ِ︎ك︎ُ︎م︎ْ︎ ر︎َ︎ح︎ْ︎م︎َ︎ة︎ٗ︎ۖ︎ و︎َ︎ل︎َ︎ا︎ ي︎َ︎ج︎ِ︎د︎ُ︎و︎ن︎َ︎ ل︎َ︎ه︎ُ︎م︎ م︎ّ︎ِ︎ن︎ د︎ُ︎و︎ن︎ِ︎ ا︎ِ︎۬︎ل︎ل︎ّ︎َ︎ه︎ِ︎ و︎َ︎ل︎ِ︎ي︎ّ︎ا︎ٗ︎ و︎َ︎ل︎َ︎ا︎ ن︎َ︎ص︎ِ︎ي︎ر︎ا︎ٗ︎ۖ︎ ١︎٧︎",
      "numberInSurah": 17,
      "verse_key": "33:17"
    },
    {
      "text": "۞︎ق︎َ︎د︎ْ︎ ي︎َ︎ع︎ْ︎ل︎َ︎م︎ُ︎ ا︎ُ︎۬︎ل︎ل︎ّ︎َ︎ه︎ُ︎ ا︎ُ︎۬︎ل︎ْ︎م︎ُ︎ع︎َ︎و︎ّ︎ِ︎ق︎ِ︎ي︎ن︎َ︎ م︎ِ︎ن︎ك︎ُ︎م︎ْ︎ و︎َ︎ا︎ل︎ْ︎ق︎َ︎ا︎ٓ︎ئ︎ِ︎ل︎ِ︎ي︎ن︎َ︎ ل︎ِ︎إ︎ِ︎خ︎ْ︎و︎َ︎ٰ︎ن︎ِ︎ه︎ِ︎م︎ْ︎ ه︎َ︎ل︎ُ︎م︎ّ︎َ︎ إ︎ِ︎ل︎َ︎ي︎ْ︎ن︎َ︎ا︎ و︎َ︎ل︎َ︎ا︎ ي︎َ︎ا︎ت︎ُ︎و︎ن︎َ︎ ا︎َ︎۬︎ل︎ْ︎ب︎َ︎أ︎ْ︎س︎َ︎ إ︎ِ︎ل︎ّ︎َ︎ا︎ ق︎َ︎ل︎ِ︎ي︎ل︎ا︎ً︎ ١︎٨︎",
      "numberInSurah": 18,
      "verse_key": "33:18"
    },
    {
      "text": "ا︎َ︎ش︎ِ︎ح︎ّ︎َ︎ة︎ً︎ ع︎َ︎ل︎َ︎ي︎ْ︎ك︎ُ︎م︎ْ︎ۖ︎ ف︎َ︎إ︎ِ︎ذ︎َ︎ا︎ ج︎َ︎ا︎ٓ︎ء︎َ︎ ا︎َ︎۬︎ل︎ْ︎خ︎َ︎و︎ْ︎ف︎ُ︎ ر︎َ︎أ︎َ︎ي︎ْ︎ت︎َ︎ه︎ُ︎م︎ْ︎ ي︎َ︎ن︎ظ︎ُ︎ر︎ُ︎و︎ن︎َ︎ إ︎ِ︎ل︎َ︎ي︎ْ︎ك︎َ︎ ت︎َ︎د︎ُ︎و︎ر︎ُ︎ أ︎َ︎ع︎ْ︎ي︎ُ︎ن︎ُ︎ه︎ُ︎م︎ْ︎ ك︎َ︎ا︎ل︎ذ︎ِ︎ے︎ ي︎ُ︎غ︎ْ︎ش︎۪︎ي︎ٰ︎ ع︎َ︎ل︎َ︎ي︎ْ︎ه︎ِ︎ م︎ِ︎ن︎َ︎ ا︎َ︎۬︎ل︎ْ︎م︎َ︎و︎ْ︎ت︎ِ︎ۖ︎ ف︎َ︎إ︎ِ︎ذ︎َ︎ا︎ ذ︎َ︎ه︎َ︎ب︎َ︎ ا︎َ︎۬︎ل︎ْ︎خ︎َ︎و︎ْ︎ف︎ُ︎ س︎َ︎ل︎َ︎ق︎ُ︎و︎ك︎ُ︎م︎ ب︎ِ︎أ︎َ︎ل︎ْ︎س︎ِ︎ن︎َ︎ة︎ٍ︎ ح︎ِ︎د︎َ︎ا︎د︎ٍ︎ ا︎َ︎ش︎ِ︎ح︎ّ︎َ︎ة︎ً︎ ع︎َ︎ل︎َ︎ي︎ ا︎َ︎۬︎ل︎ْ︎خ︎َ︎ي︎ْ︎ر︎ِ︎ۖ︎ أ︎ُ︎و︎ْ︎ل︎َ︎ٰ︎ٓ︎ئ︎ِ︎ك︎َ︎ ل︎َ︎م︎ْ︎ ي︎ُ︎و︎م︎ِ︎ن︎ُ︎و︎ا︎ْ︎ ف︎َ︎أ︎َ︎ح︎ْ︎ب︎َ︎ط︎َ︎ ا︎َ︎۬︎ل︎ل︎ّ︎َ︎ه︎ُ︎ أ︎َ︎ع︎ْ︎م︎َ︎ٰ︎ل︎َ︎ه︎ُ︎م︎ْ︎ۖ︎ و︎َ︎ك︎َ︎ا︎ن︎َ︎ ذ︎َ︎ٰ︎ل︎ِ︎ك︎َ︎ ع︎َ︎ل︎َ︎ي︎ ا︎َ︎۬︎ل︎ل︎ّ︎َ︎ه︎ِ︎ ي︎َ︎س︎ِ︎ي︎ر︎ا︎ٗ︎ۖ︎ ١︎٩︎",
      "numberInSurah": 19,
      "verse_key": "33:19"
    },
    {
      "text": "ي︎َ︎ح︎ْ︎س︎ِ︎ب︎ُ︎و︎ن︎َ︎ ا︎َ︎۬︎ل︎َ︎ا︎ح︎ْ︎ز︎َ︎ا︎ب︎َ︎ ل︎َ︎م︎ْ︎ ي︎َ︎ذ︎ْ︎ه︎َ︎ب︎ُ︎و︎ا︎ْ︎ۖ︎ و︎َ︎إ︎ِ︎ن︎ْ︎ ي︎ّ︎َ︎ا︎ت︎ِ︎ ا︎ِ︎۬︎ل︎َ︎ا︎ح︎ْ︎ز︎َ︎ا︎ب︎ُ︎ ي︎َ︎و︎َ︎د︎ّ︎ُ︎و︎ا︎ْ︎ ل︎َ︎و︎َ︎ ا︎َ︎ن︎ّ︎َ︎ه︎ُ︎م︎ ب︎َ︎ا︎د︎ُ︎و︎ن︎َ︎ ف︎ِ︎ے︎ ا︎ِ︎۬︎ل︎َ︎ا︎ع︎ْ︎ر︎َ︎ا︎ب︎ِ︎ۖ︎ ي︎َ︎س︎ْ︎ـ︎ٔ︎َ︎ل︎ُ︎و︎ن︎َ︎ ع︎َ︎ن︎َ︎ ا︎َ︎ن︎ۢ︎ب︎َ︎ا︎ٓ︎ئ︎ِ︎ك︎ُ︎م︎ْ︎ و︎َ︎ل︎َ︎و︎ْ︎ ك︎َ︎ا︎ن︎ُ︎و︎ا︎ْ︎ ف︎ِ︎ي︎ك︎ُ︎م︎ م︎ّ︎َ︎ا︎ ق︎َ︎ٰ︎ت︎َ︎ل︎ُ︎و︎ٓ︎ا︎ْ︎ إ︎ِ︎ل︎ّ︎َ︎ا︎ ق︎َ︎ل︎ِ︎ي︎ل︎ا︎ٗ︎ۖ︎ ٢︎٠︎",
      "numberInSurah": 20,
      "verse_key": "33:20"
    },
    {
      "text": "ل︎ّ︎َ︎ق︎َ︎د︎ْ︎ ك︎َ︎ا︎ن︎َ︎ ل︎َ︎ك︎ُ︎م︎ْ︎ ف︎ِ︎ے︎ ر︎َ︎س︎ُ︎و︎ل︎ِ︎ ا︎ِ︎۬︎ل︎ل︎ّ︎َ︎ه︎ِ︎ إ︎ِ︎س︎ْ︎و︎َ︎ة︎ٌ︎ ح︎َ︎س︎َ︎ن︎َ︎ة︎ٞ︎ ل︎ّ︎ِ︎م︎َ︎ن︎ ك︎َ︎ا︎ن︎َ︎ ي︎َ︎ر︎ْ︎ج︎ُ︎و︎ا︎ْ︎ ا︎ُ︎۬︎ل︎ل︎ّ︎َ︎ه︎َ︎ و︎َ︎ا︎ل︎ْ︎ي︎َ︎و︎ْ︎م︎َ︎ ا︎َ︎۬︎ل︎َ︎ا︎خ︎ِ︎ر︎َ︎ و︎َ︎ذ︎َ︎ك︎َ︎ر︎َ︎ ا︎َ︎۬︎ل︎ل︎ّ︎َ︎ه︎َ︎ ك︎َ︎ث︎ِ︎ي︎ر︎ا︎ٗ︎ۖ︎ ٢︎١︎",
      "numberInSurah": 21,
      "verse_key": "33:21"
    },
    {
      "text": "و︎َ︎ل︎َ︎م︎ّ︎َ︎ا︎ ر︎َ︎ء︎َ︎ا︎ ا︎َ︎۬︎ل︎ْ︎م︎ُ︎و︎م︎ِ︎ن︎ُ︎و︎ن︎َ︎ ا︎َ︎۬︎ل︎َ︎ا︎ح︎ْ︎ز︎َ︎ا︎ب︎َ︎ ق︎َ︎ا︎ل︎ُ︎و︎ا︎ْ︎ ه︎َ︎ٰ︎ذ︎َ︎ا︎ م︎َ︎ا︎ و︎َ︎ع︎َ︎د︎َ︎ن︎َ︎ا︎ ا︎َ︎۬︎ل︎ل︎ّ︎َ︎ه︎ُ︎ و︎َ︎ر︎َ︎س︎ُ︎و︎ل︎ُ︎ه︎ُ︎ۥ︎ و︎َ︎ص︎َ︎د︎َ︎ق︎َ︎ ا︎َ︎۬︎ل︎ل︎ّ︎َ︎ه︎ُ︎ و︎َ︎ر︎َ︎س︎ُ︎و︎ل︎ُ︎ه︎ُ︎ۥ︎ۖ︎ و︎َ︎م︎َ︎ا︎ ز︎َ︎ا︎د︎َ︎ه︎ُ︎م︎ُ︎ۥ︎ٓ︎ إ︎ِ︎ل︎ّ︎َ︎ا︎ٓ︎ إ︎ِ︎ي︎م︎َ︎ٰ︎ن︎ا︎ٗ︎ و︎َ︎ت︎َ︎س︎ْ︎ل︎ِ︎ي︎م︎ا︎ٗ︎ۖ︎ ٢︎٢︎",
      "numberInSurah": 22,
      "verse_key": "33:22"
    }
  ],
  "source": {
    "type": "warsh-quran-apk",
    "timestamp": "2026-04-27T01:25:12.313Z"
  }
}