{
  "pageNumber": 505,
  "riwayaId": "warsh",
  "ayahs": [
    {
      "text": "ق︎َ︎ا︎ل︎ُ︎و︎ٓ︎ا︎ْ︎ أ︎َ︎ج︎ِ︎ي︎ٔ︎ْ︎ت︎َ︎ن︎َ︎ا︎ ل︎ِ︎ت︎َ︎ا︎ف︎ِ︎ك︎َ︎ن︎َ︎ا︎ ع︎َ︎ن︎َ︎ ا︎ٰ︎ل︎ِ︎ه︎َ︎ت︎ِ︎ن︎َ︎ا︎ ف︎َ︎ا︎ت︎ِ︎ن︎َ︎ا︎ ب︎ِ︎م︎َ︎ا︎ ت︎َ︎ع︎ِ︎د︎ُ︎ن︎َ︎ا︎ٓ︎ إ︎ِ︎ن︎ ك︎ُ︎ن︎ت︎َ︎ م︎ِ︎ن︎َ︎ ا︎َ︎۬︎ل︎ص︎ّ︎َ︎ٰ︎د︎ِ︎ق︎ِ︎ي︎ن︎َ︎ۖ︎ ٢︎١︎",
      "numberInSurah": 21,
      "verse_key": "46:21"
    },
    {
      "text": "ق︎َ︎ا︎ل︎َ︎ إ︎ِ︎ن︎ّ︎َ︎م︎َ︎ا︎ ا︎َ︎۬︎ل︎ْ︎ع︎ِ︎ل︎ْ︎م︎ُ︎ ع︎ِ︎ن︎د︎َ︎ ا︎َ︎۬︎ل︎ل︎ّ︎َ︎ه︎ِ︎ و︎َ︎أ︎ُ︎ب︎َ︎ل︎ّ︎ِ︎غ︎ُ︎ك︎ُ︎م︎ م︎ّ︎َ︎ا︎ٓ︎ أ︎ُ︎ر︎ْ︎س︎ِ︎ل︎ْ︎ت︎ُ︎ ب︎ِ︎ه︎ِ︎ۦ︎ و︎َ︎ل︎َ︎ٰ︎ك︎ِ︎ن︎ّ︎ِ︎ي︎َ︎ أ︎َ︎ر︎۪︎ي︎ٰ︎ك︎ُ︎م︎ْ︎ ق︎َ︎و︎ْ︎م︎ا︎ٗ︎ ت︎َ︎ج︎ْ︎ه︎َ︎ل︎ُ︎و︎ن︎َ︎ۖ︎ ٢︎٢︎",
      "numberInSurah": 22,
      "verse_key": "46:22"
    },
    {
      "text": "ف︎َ︎ل︎َ︎م︎ّ︎َ︎ا︎ ر︎َ︎أ︎َ︎و︎ْ︎ه︎ُ︎ ع︎َ︎ا︎ر︎ِ︎ض︎ا︎ٗ︎ م︎ّ︎ُ︎س︎ْ︎ت︎َ︎ق︎ْ︎ب︎ِ︎ل︎َ︎ أ︎َ︎و︎ْ︎د︎ِ︎ي︎َ︎ت︎ِ︎ه︎ِ︎م︎ْ︎ ق︎َ︎ا︎ل︎ُ︎و︎ا︎ْ︎ ه︎َ︎ٰ︎ذ︎َ︎ا︎ ع︎َ︎ا︎ر︎ِ︎ض︎ٞ︎ م︎ّ︎ُ︎م︎ْ︎ط︎ِ︎ر︎ُ︎ن︎َ︎ا︎ۖ︎ ب︎َ︎ل︎ْ︎ ه︎ُ︎و︎َ︎ م︎َ︎ا︎ ا︎َ︎۪︎س︎ْ︎ت︎َ︎ع︎ْ︎ج︎َ︎ل︎ْ︎ت︎ُ︎م︎ ب︎ِ︎ه︎ِ︎ۦ︎ۖ︎ ر︎ِ︎ي︎ح︎ٞ︎ ف︎ِ︎ي︎ه︎َ︎ا︎ ع︎َ︎ذ︎َ︎ا︎ب︎ٌ︎ ا︎َ︎ل︎ِ︎ي︎م︎ٞ︎ۖ︎ ٢︎٣︎",
      "numberInSurah": 23,
      "verse_key": "46:23"
    },
    {
      "text": "ت︎ُ︎د︎َ︎م︎ّ︎ِ︎ر︎ُ︎ ك︎ُ︎ل︎ّ︎َ︎ ش︎َ︎ے︎ْ︎ء︎ِ︎ۢ︎ ب︎ِ︎أ︎َ︎م︎ْ︎ر︎ِ︎ ر︎َ︎ب︎ّ︎ِ︎ه︎َ︎ا︎ ف︎َ︎أ︎َ︎ص︎ْ︎ب︎َ︎ح︎ُ︎و︎ا︎ْ︎ ل︎َ︎ا︎ ت︎َ︎ر︎۪︎ي︎ٰ︎ٓ︎ إ︎ِ︎ل︎ّ︎َ︎ا︎ م︎َ︎س︎َ︎ٰ︎ك︎ِ︎ن︎َ︎ه︎ُ︎م︎ْ︎ۖ︎ ك︎َ︎ذ︎َ︎ٰ︎ل︎ِ︎ك︎َ︎ ن︎َ︎ج︎ْ︎ز︎ِ︎ے︎ ا︎ِ︎۬︎ل︎ْ︎ق︎َ︎و︎ْ︎م︎َ︎ ا︎َ︎۬︎ل︎ْ︎م︎ُ︎ج︎ْ︎ر︎ِ︎م︎ِ︎ي︎ن︎َ︎ۖ︎ ٢︎٤︎",
      "numberInSurah": 24,
      "verse_key": "46:24"
    },
    {
      "text": "و︎َ︎ل︎َ︎ق︎َ︎د︎ْ︎ م︎َ︎ك︎ّ︎َ︎ن︎ّ︎َ︎ٰ︎ه︎ُ︎م︎ْ︎ ف︎ِ︎ي︎م︎َ︎ا︎ٓ︎ إ︎ِ︎ن︎ م︎ّ︎َ︎ك︎ّ︎َ︎ن︎ّ︎َ︎ٰ︎ك︎ُ︎م︎ْ︎ ف︎ِ︎ي︎ه︎ِ︎ و︎َ︎ج︎َ︎ع︎َ︎ل︎ْ︎ن︎َ︎ا︎ ل︎َ︎ه︎ُ︎م︎ْ︎ س︎َ︎م︎ْ︎ع︎ا︎ٗ︎ و︎َ︎أ︎َ︎ب︎ْ︎ص︎َ︎ٰ︎ر︎ا︎ٗ︎ و︎َ︎أ︎َ︎ف︎ْ︎ـ︎ٕ︎ِ︎د︎َ︎ة︎ٗ︎ ف︎َ︎م︎َ︎ا︎ٓ︎ أ︎َ︎غ︎ْ︎ن︎۪︎ي︎ٰ︎ ع︎َ︎ن︎ْ︎ه︎ُ︎م︎ْ︎ س︎َ︎م︎ْ︎ع︎ُ︎ه︎ُ︎م︎ْ︎ و︎َ︎ل︎َ︎ا︎ٓ︎ أ︎َ︎ب︎ْ︎ص︎َ︎ٰ︎ر︎ُ︎ه︎ُ︎م︎ْ︎ و︎َ︎ل︎َ︎ا︎ٓ︎ أ︎َ︎ف︎ْ︎ـ︎ٕ︎ِ︎د︎َ︎ت︎ُ︎ه︎ُ︎م︎ م︎ّ︎ِ︎ن︎ ش︎َ︎ے︎ْ︎ء︎ٍ︎ ا︎ِ︎ذ︎ْ︎ ك︎َ︎ا︎ن︎ُ︎و︎ا︎ْ︎ ي︎َ︎ج︎ْ︎ح︎َ︎د︎ُ︎و︎ن︎َ︎ ب︎ِ︎ـ︎ٔ︎َ︎ا︎ي︎َ︎ٰ︎ت︎ِ︎ ا︎ِ︎۬︎ل︎ل︎ّ︎َ︎ه︎ِ︎ و︎َ︎ح︎َ︎ا︎ق︎َ︎ ب︎ِ︎ه︎ِ︎م︎ م︎ّ︎َ︎ا︎ ك︎َ︎ا︎ن︎ُ︎و︎ا︎ْ︎ ب︎ِ︎ه︎ِ︎ۦ︎ ي︎َ︎س︎ْ︎ت︎َ︎ه︎ْ︎ز︎ِ︎ء︎ُ︎و︎ن︎َ︎ۖ︎ ٢︎٥︎",
      "numberInSurah": 25,
      "verse_key": "46:25"
    },
    {
      "text": "و︎َ︎ل︎َ︎ق︎َ︎د︎َ︎ ا︎َ︎ه︎ْ︎ل︎َ︎ك︎ْ︎ن︎َ︎ا︎ م︎َ︎ا︎ ح︎َ︎و︎ْ︎ل︎َ︎ك︎ُ︎م︎ م︎ّ︎ِ︎ن︎َ︎ ا︎َ︎۬︎ل︎ْ︎ق︎ُ︎ر︎۪︎ي︎ٰ︎ و︎َ︎ص︎َ︎ر︎ّ︎َ︎ف︎ْ︎ن︎َ︎ا︎ ا︎َ︎۬︎ل︎َ︎ا︎ي︎َ︎ٰ︎ت︎ِ︎ ل︎َ︎ع︎َ︎ل︎ّ︎َ︎ه︎ُ︎م︎ْ︎ ي︎َ︎ر︎ْ︎ج︎ِ︎ع︎ُ︎و︎ن︎َ︎ۖ︎ ٢︎٦︎",
      "numberInSurah": 26,
      "verse_key": "46:26"
    },
    {
      "text": "ف︎َ︎ل︎َ︎و︎ْ︎ل︎َ︎ا︎ ن︎َ︎ص︎َ︎ر︎َ︎ه︎ُ︎م︎ُ︎ ا︎ُ︎۬︎ل︎ذ︎ِ︎ي︎ن︎َ︎ ا︎َ︎۪︎ت︎ّ︎َ︎خ︎َ︎ذ︎ُ︎و︎ا︎ْ︎ م︎ِ︎ن︎ د︎ُ︎و︎ن︎ِ︎ ا︎ِ︎۬︎ل︎ل︎ّ︎َ︎ه︎ِ︎ ق︎ُ︎ر︎ْ︎ب︎َ︎ا︎ن︎ا︎ً︎ ا︎ٰ︎ل︎ِ︎ه︎َ︎ة︎َ︎ۢ︎ۖ︎ ب︎َ︎ل︎ْ︎ ض︎َ︎ل︎ّ︎ُ︎و︎ا︎ْ︎ ع︎َ︎ن︎ْ︎ه︎ُ︎م︎ْ︎ۖ︎ و︎َ︎ذ︎َ︎ٰ︎ل︎ِ︎ك︎َ︎ إ︎ِ︎ف︎ْ︎ك︎ُ︎ه︎ُ︎م︎ْ︎ و︎َ︎م︎َ︎ا︎ ك︎َ︎ا︎ن︎ُ︎و︎ا︎ْ︎ ي︎َ︎ف︎ْ︎ت︎َ︎ر︎ُ︎و︎ن︎َ︎ۖ︎ ٢︎٧︎",
      "numberInSurah": 27,
      "verse_key": "46:27"
    },
    {
      "text": "و︎َ︎إ︎ِ︎ذ︎ْ︎ ص︎َ︎ر︎َ︎ف︎ْ︎ن︎َ︎ا︎ٓ︎ إ︎ِ︎ل︎َ︎ي︎ْ︎ك︎َ︎ ن︎َ︎ف︎َ︎ر︎ا︎ٗ︎ م︎ّ︎ِ︎ن︎َ︎ ا︎َ︎۬︎ل︎ْ︎ج︎ِ︎ن︎ّ︎ِ︎ ي︎َ︎س︎ْ︎ت︎َ︎م︎ِ︎ع︎ُ︎و︎ن︎َ︎ ا︎َ︎۬︎ل︎ْ︎ق︎ُ︎ر︎ْ︎ء︎َ︎ا︎ن︎َ︎ ف︎َ︎ل︎َ︎م︎ّ︎َ︎ا︎ ح︎َ︎ض︎َ︎ر︎ُ︎و︎ه︎ُ︎ ق︎َ︎ا︎ل︎ُ︎و︎ٓ︎ا︎ْ︎ أ︎َ︎ن︎ص︎ِ︎ت︎ُ︎و︎ا︎ْ︎ۖ︎ ف︎َ︎ل︎َ︎م︎ّ︎َ︎ا︎ ق︎ُ︎ض︎ِ︎ي︎َ︎ و︎َ︎ل︎ّ︎َ︎و︎ِ︎ا︎ْ︎ ا︎ِ︎ل︎َ︎ي︎ٰ︎ ق︎َ︎و︎ْ︎م︎ِ︎ه︎ِ︎م︎ م︎ّ︎ُ︎ن︎ذ︎ِ︎ر︎ِ︎ي︎ن︎َ︎ۖ︎ ٢︎٨︎",
      "numberInSurah": 28,
      "verse_key": "46:28"
    }
  ],
  "source": {
    "type": "warsh-quran-apk",
    "timestamp": "2026-04-27T01:25:21.042Z"
  }
}